openapi_client/__init__.py
openapi_client/api_client.py
openapi_client/api_response.py
openapi_client/configuration.py
openapi_client/exceptions.py
openapi_client/py.typed
openapi_client/rest.py
openapi_client/api/__init__.py
openapi_client/api/employees_api.py
openapi_client/api/payroll_automation_api.py
openapi_client/api/placeholders_future_features_api.py
openapi_client/api/roles_configuration_api.py
openapi_client/models/__init__.py
openapi_client/models/create_employee.py
openapi_client/models/create_role_request.py
openapi_client/models/employee.py
openapi_client/models/leave_policy.py
openapi_client/models/leave_policy_deduction.py
openapi_client/models/overtime_policy.py
openapi_client/models/payroll_calculation_result.py
openapi_client/models/role_configuration.py
openapi_client/models/salary_info.py
dibbayajyotiroy_payroll_sdk-0.1.0.dist-info/METADATA
dibbayajyotiroy_payroll_sdk-0.1.0.dist-info/WHEEL
dibbayajyotiroy_payroll_sdk-0.1.0.dist-info/top_level.txt
dibbayajyotiroy_payroll_sdk-0.1.0.dist-info/RECORD
