Metadata-Version: 2.4
Name: dibbayajyotiroy-payroll-sdk
Version: 0.1.0
Summary: A client SDK for the Rust Payroll System API.
Home-page: https://github.com/DibbayajyotiRoy/Payroll-Management-System
Author: Dibbayajyoti Roy
Author-email: Your Name <your.email@example.com>
License: MIT
Project-URL: Homepage, https://github.com/your-username/your-repo
Project-URL: Bug Tracker, https://github.com/your-username/your-repo/issues
Classifier: Programming Language :: Python :: 3
Classifier: License :: OSI Approved :: MIT License
Classifier: Operating System :: OS Independent
Requires-Python: >=3.7
Dynamic: author
Dynamic: home-page
